aioartifactory/__init__.py
aioartifactory/aioartifactory.py
aioartifactory/cli.py
aioartifactory/common.py
aioartifactory/configuration.py
aioartifactory/context.py
aioartifactory/localpath.py
aioartifactory/remotepath.py
aioartifactory-0.1.2.dist-info/LICENSE
aioartifactory-0.1.2.dist-info/METADATA
aioartifactory-0.1.2.dist-info/WHEEL
aioartifactory-0.1.2.dist-info/top_level.txt
aioartifactory-0.1.2.dist-info/RECORD
