Metadata-Version: 2.2
Name: aioartifactory
Version: 0.1.2
Summary: Asynchronous Input Output (AIO) Artifactory
Author: Yan Kuang
License: MIT License
Project-URL: Homepage, https://github.com/YTKme/aioartifactory
Project-URL: Bug Tracker, https://github.com/YTKme/aioartifactory/issues
Keywords: aioartifactory
Classifier: Development Status :: 3 - Alpha
Classifier: Intended Audience :: Developers
Classifier: Topic :: Software Development :: Libraries
Classifier: License :: OSI Approved :: MIT License
Classifier: Programming Language :: Python :: 3
Classifier: Programming Language :: Python :: 3.11
Classifier: Programming Language :: Python :: 3.12
Requires-Python: >=3.11
License-File: LICENSE
Requires-Dist: aiofiles
Requires-Dist: aiohttp[speedups]
Requires-Dist: tealogger
Provides-Extra: develop
Requires-Dist: build; extra == "develop"
Requires-Dist: pytest-asyncio; extra == "develop"
Requires-Dist: pytest-cov; extra == "develop"
Requires-Dist: pytest; extra == "develop"
Requires-Dist: ruff; extra == "develop"
Requires-Dist: twine; extra == "develop"
Provides-Extra: test
Requires-Dist: pytest-asyncio; extra == "test"
Requires-Dist: pytest-cov; extra == "test"
Requires-Dist: pytest; extra == "test"
Requires-Dist: ruff; extra == "test"
